dora_camera_opencv/main.py
dora_camera_opencv-0.0.1.dist-info/METADATA
dora_camera_opencv-0.0.1.dist-info/WHEEL
dora_camera_opencv-0.0.1.dist-info/entry_points.txt
dora_camera_opencv-0.0.1.dist-info/top_level.txt
dora_camera_opencv-0.0.1.dist-info/RECORD
