Metadata-Version: 2.4
Name: dora-camera-opencv
Version: 0.0.1
Summary: Dora Node for OpenCV Camera
Author-email: Xiang Yang <ryu-yang@qq.com>
Requires-Python: <3.14,>=3.8
Requires-Dist: dora-rs<0.4.0,>=0.3.11
Requires-Dist: opencv-python>=4.1.1
Requires-Dist: numpy
